taskflow_work/__init__.py
taskflow_work/core.py
taskflow_work-0.1.1.dist-info/METADATA
taskflow_work-0.1.1.dist-info/WHEEL
taskflow_work-0.1.1.dist-info/top_level.txt
taskflow_work-0.1.1.dist-info/RECORD
